{
  "id": "trinium-chat-buttons",
  "title": "Trinium Chat Buttons",
  "description": "Adds compact buttons below the chat with a few convenient features: roll modifiers, a mini combat tracker and customizable GM screen!",
  "version": "1.5.1",
  "authors": [
    {
      "name": "Andrea Gomez",
      "discord": "angometry",
      "url": "https://github.com/TheDarkTongo",
      "flags": {}
    }
  ],
  "languages": [
    {
      "lang": "en",
      "name": "English",
      "path": "lang/en.json",
      "flags": {}
    }
  ],
  "scripts": [
    "lib/marked-min.js"
  ],
  "esmodules": [
    "src/templates/gm-screen-presets.js",

    "src/module/settings.js",
    "src/module/logger.js",

    "src/utils/draggable.js",
    "src/utils/confirmation-dialog.js",
    "src/utils/journal-entry-renderer.js",
    "src/utils/notification.js",

    "src/module/chat-buttons/roll-privacy.js",
    "src/module/chat-buttons/gm-screen.js",
    "src/module/chat-buttons/midi.js",
    "src/module/chat-buttons/combat-tracker.js",
    "src/module/chat-buttons/utility.js",
    
    "src/trinium-chat-buttons.js"
  ],
  "styles": [
    "styles/chat-buttons.css",
    "styles/gm-screen.css",
    "styles/combat-tracker.css"
  ],
  "url": "https://github.com/thedarktongo/trinium-chat-buttons",
  "manifest": "https://raw.githubusercontent.com/TheDarkTongo/trinium-chat-buttons/main/module.json",
  "download": "https://github.com/TheDarkTongo/trinium-chat-buttons/archive/refs/heads/main.zip",
  "compatibility": {
    "minimum": "11",
    "verified": "12"
  }
}